{
  "version": "5",
  "dialect": "sqlite",
  "id": "c43681bd-885d-424a-86fe-0f87b9282377",
  "prevId": "00000000-0000-0000-0000-000000000000",
  "tables": {
    "player": {
      "name": "player",
      "columns": {
        "snowflake": {
          "name": "snowflake",
          "type": "text",
          "primaryKey": true,
          "notNull": true,
          "autoincrement": false
        },
        "team_snowflake": {
          "name": "team_snowflake",
          "type": "text",
          "primaryKey": false,
          "notNull": true,
          "autoincrement": false
        },
        "score": {
          "name": "score",
          "type": "integer",
          "primaryKey": false,
          "notNull": true,
          "autoincrement": false,
          "default": 0
        }
      },
      "indexes": {},
      "foreignKeys": {
        "player_team_snowflake_team_snowflake_fk": {
          "name": "player_team_snowflake_team_snowflake_fk",
          "tableFrom": "player",
          "tableTo": "team",
          "columnsFrom": [
            "team_snowflake"
          ],
          "columnsTo": [
            "snowflake"
          ],
          "onDelete": "no action",
          "onUpdate": "no action"
        }
      },
      "compositePrimaryKeys": {},
      "uniqueConstraints": {}
    },
    "team": {
      "name": "team",
      "columns": {
        "snowflake": {
          "name": "snowflake",
          "type": "text",
          "primaryKey": true,
          "notNull": true,
          "autoincrement": false
        }
      },
      "indexes": {},
      "foreignKeys": {},
      "compositePrimaryKeys": {},
      "uniqueConstraints": {}
    }
  },
  "enums": {},
  "_meta": {
    "schemas": {},
    "tables": {},
    "columns": {}
  }
}